flet/__init__.py
flet/canvas/__init__.py
flet/flet.py
flet/matplotlib_chart.py
flet/plotly_chart.py
flet/pyodide_connection.py
flet/version.py
flet_pyodide-0.24.1.dist-info/METADATA
flet_pyodide-0.24.1.dist-info/WHEEL
flet_pyodide-0.24.1.dist-info/RECORD
